[
    {
        "id": 1376,
        "title": "【征婚】33岁，女，成熟，顾家——期待的另一半婚姻状况不限，有一定的经济基础",
        "content": "点击进入→：找工作、找房子、找商家、招人才、买卖二手物品这里通通都有！竹溪最有效的信息平台！点击上方一键订发布【婚恋网】会员推荐（照片来源于婚恋网属本人上传）美女推荐户籍：竹溪年龄：33身高：160体重：50工作：自由职业月薪：2000房车：与父母同住自我介绍： 成熟，顾家理想另一半： 婚姻状况不限，有一定经济基础，不抽烟赌博，有爱心，善良诚实，有事业心和上进心。对这位帅哥有意向的，可以联系红娘帮你牵线识别二维码添加红娘微信如何成为推荐嘉宾添加红娘微信，告诉红娘你需要被推荐平台推荐须知推荐要求：必须是竹溪的单身男女，一旦发现伪单身或信息虚假，立即拉黑注销。资料准备：请将个人姓名、年龄、身高、职业、择偶要求、联系方式及自我介绍，发给竹溪婚恋网红娘客服。至少附3张个人照片（生活照、写真照均可）如何快速脱单快来竹溪婚恋网交友平台，本平台聚集有大量的竹溪优质单身男女，本平台会员有上班族、个体工商户、企事业人员、公务员等公告为了保证【竹溪婚恋网】会员资料的真实性，有效性。要求所有参与征婚活动人员必须填写本人真实完整的资料！拒绝填写虚假资料，否则客服不予通过，头像必须是本人照片，不可上传风景、动物图像等，否则客服有权删除，资料必须真实可靠，已婚人士勿扰！产生任何家庭矛盾或社会影响后果自负！请勿轻易汇款汇物！提高谨慎，避免上当受骗！",
        "author": "竹溪圈",
        "time": "2018-04-14 17:31"
    }
]