[
    {
        "id": 18,
        "title": "人们的经历是怎样影响自己的婚恋观念的？",
        "content": "一、案例有个朋友咨询我的时候，说她的一个阿姨介绍一个条件不错的男的给她，当她听到这个男的离过婚，就一口回绝了。阿姨说“离婚没事的。”但是她根本就没有兴趣听下去。因为这个朋友没有结过婚，就谈过一次恋爱，各方面的条件不错，也谈不上“嫁不出去”，所以对于有过婚姻的，她根本不会考虑。这是很好理解的。一般没有结过婚的，很难选择有婚姻史的，除非极少数人不介意有婚史。这就是在恋爱婚姻条件的“对等”吧？就和“门当户对”一样，人们一般考虑自身物质条件、经历、三观与自己基本上相似的。从另一个角度来理解，这也是说明了人们的经历影响着自己的婚恋观念。二、恋爱婚姻条件的“对等”一些处男处女谈朋友的时候，有些人可能在开始的时候，会介意对方有没有过性关系。如果已经不是处男处女了，也就往往不那么在意了。对于有过婚史的人来说，在考虑再婚的时候，往往根本不会在意对方有没有结过婚？而且更加注意适不适合？往往会适当放低要求，因为有个人陪伴会增加安全感。绝大多数再婚的人，选择结婚的对象往往是离异或者丧偶的。对于有过离异或者丧偶经历的人来说，经历了离婚和丧偶的变故，内心受到一定的打击，对婚姻的观念会发生一定的改变，往往对再婚的对象会宽容一些。在两性关系和婚姻的经历上，往往选择比较“对等”的，这是最“合理”的选择。但是，难免有时候，这些观念的束缚会限制自己的行动。三、三个再婚的故事1.有个大哥离婚了，主要是“性格不合”。两个人在一起经常吵架，不不想让，结婚不到两年就离婚了。后来，他参加了一个日语培训班，认识了一个女孩，两个人很能聊得来，他告诉她，他离过婚。开始，这个女孩也很在意这一点，但是，由于大家在一起学习日语，经常见面，她觉得和他做个朋友也不错。时间长了，两个人相处融洽，女孩也不再介意他的婚姻史了。最后，最后两个人结婚，也很幸福。2.有个四川的大姐18岁的时候，一个人来到北京，20岁的时候嫁给同样在北京工作的四川老乡，两个人生了一个女儿，但是，此后两个人经常吵架，他们脾气都很火爆，于是离婚，女儿由男方抚养。离婚后，大姐工作了两年，后来遇到一个北京本地人，他们谈了一个月，就结婚了。她的后来老公对她非常好，脾气也很好，不介意她结过婚，还主动和父母隐瞒她的婚姻史。后来，他们有了一个儿子。她的女儿上大学后，也经常去她家玩，两姐弟的感情也非常好。3.我外婆曾经对我说，她老公因病去世的时候，正是在“三年自然灾害”时期，她也饿的不行了，外公找到了她，把她带回家。外公原配也因病去世，留下一个孩子，也就是我大舅伯。于是，两个人早出晚归，又生了四个女儿一个儿子，都抚养长大成家，其中我二姨还考上了大学。这是我身边的亲友的三个再婚的故事，他们都因为再婚找到了自己的幸福。虽然他们曾经走过弯路，但是，这些经历让他们重新选择的时候，更加懂得珍惜现在的生活，感恩伴侣的选择。四、幸福——殊途共归在第一个故事里，我的朋友如果没有参加日语培训，那么，估计他和她后来的老婆也不会有机会，因为她老婆之前从来不会考虑过会和离婚的男士结婚。但是，由于培训了解了彼此，才发现遇见了合适的人，其他的条件也许根本就是多余。在第二个故事里，我的大姐似乎“运气”非常的好，因为第二任老公脾气很好，不介意她的婚史，还向自己的父母隐瞒她的婚史（直到现在父母也不知道），对她的第一个女儿也很好。大姐非常能干，对父母也很孝顺，很好的融入了北京的生活。在第三个故事里，外公和外婆在各自人生不如意的时刻相遇，相互鼓励，终于走出了阴影，养大了六个孩子，又给了孙辈们很多关爱，受到子孙们的敬爱。在生活中，人们会给自己的婚恋设置各种各样的“条件”：身高、体重、长相、地域、宗教、生肖、经济条件、学历、三观、父母的背景、职业、性格、生活习惯、婚姻史等等。但是，往往各个方面都“匹配”的情况似乎比较难得找到。很多的限制是因为自己经历造成了思维的局限。其实，如果找到了“对”的人，很多限制条件也许就是多余的。那个所谓“对”的人，真正遇见的时候，也许不像想象的那样完美，但是，能聊的来，双方“互不嫌弃”，都把对方当成“手心里的宝”，愿意执子之手与子偕老，那么，这也就是“爱情”了吧！随大流通常是“安全”的，但是，并不能一定达到目的。也许，通向婚姻恋爱幸福和快乐的路，没有统一的道路，每个人不是完全一样的，希望都能殊途同归。",
        "author": "心科学心理咨询",
        "time": "2018-11-25 23:23"
    }
]