[
    {
        "id": 202,
        "title": "朝鲜观察，朝鲜美女的择偶标准是怎样的？",
        "content": "到朝鲜旅行，见到的第一个朝鲜美女是我们导游。导游姓金，是个标准的朝鲜美女。金导大眼睛，高鼻梁，鹅蛋脸，身材苗条，声音动人。金导年芳24岁，青春洋溢。和我们在一起的几天时间，金导做事虽然认真负责，但看起来似乎有心事。和金导熟悉后，我问金导怎么了。金导敞开心扉，说出了自己的苦恼。原来金导正在为恋爱问题苦恼，金导告诉我，她和交往了两年的男朋友分手了。谈到分手的原因，金导表示因为双方父母不同意。金导的父母都在医院工作，有一定的身份地位。父母希望她找一个医生当男朋友。我问金导的择偶标准，金导说出了自己的理想对象。身高一米七以上，上过大学，有温暖的笑容，最好是单眼皮。我问金导为什么选择单眼皮男生，金导羞涩地回答，单眼皮男生很有魅力。在朝鲜半岛流行一句话，南男北女。谈到韩国男生，金导坦言他们很帅气，但不是朝鲜女孩喜欢的类型。为了找到理想的对象，朝鲜女孩也会相亲。朝鲜人把相亲称为青年男女介绍会。金导说，比起相亲，她更渴望自由恋爱，她和前男友就是自由恋爱。在中国情侣约会，往往是男生为恋爱买单，付出得更多。朝鲜男女确定恋爱关系后，是双方为恋爱买单。他们外出消费，通常实行AA制，女生不会光想着占男生便宜。电影院和公园，是朝鲜情侣经常约会的地点。朝鲜年轻人还喜欢滑旱冰，很多情侣喜欢到旱冰场约会。因为滑旱冰的时候，可以手牵手，有肢体上的接触，增进双方的感情。金导说自己虽然不会滑旱冰，但和前男友在一起的时候，她喜欢坐在一旁看男朋友滑旱冰，那种感觉非常美妙。问金导朝鲜女孩择偶的通用标准，金导说上过大学，当过兵，入过党的男生，任何朝鲜女生都会喜欢。",
        "author": "半岛客",
        "time": "2025-03-30 08:10"
    }
]