[
    {
        "id": 275,
        "title": "吴艳妮首谈择偶标准：一定要会做饭、能扛我一拳、支持我的事业",
        "content": "..............................文末才精彩................................跨越栏架，不止于田径场她说：＂我找男朋友首先一定要会做饭，第二个就是扛得住我一拳＂。这句话一出，全网沸腾。她是谁？四川妹子吴艳妮，那个在赛道上如闪电般奔驰的跨栏女神。当采访镜头对准她，本该紧张的场合，她却轻松应对。＂其实我已经有面包了，我比较向往爱情＂，自信的语气里藏着当代独立女性的闪光点。这位1999年出生的姑娘，从小学到大学全都保送，如今已是北京体育大学的在读研究生，而她的日常却不止于学术和训练。年纪轻轻就已是四川省首位获得巴黎奥运会参赛资格的运动员，在奥运赛场上跑出12.87秒的成绩，创造了中国女子100米栏的奥运会最佳记录！01＂我更想要支持我事业、支持我梦想的那个人＂，这是她对爱情的期许。在传统观念里，女孩子往往被要求为爱情牺牲事业，而她却颠覆了这一切。她的三条择偶标准——会做饭、能扛一拳、支持事业，看似简单，实则深藏玄机。这哪是在找男友，分明是在寻觅生活的共同体，力量的平等者，梦想的同行人。赛场上的她，指天扭肩的标志性动作让人过目难忘。这个看似张扬的庆祝，其实是在向过世的外公致敬，也是给自己打气的方式。当被质疑想＂当网红＂时，她干脆利落地回应：＂我不缺钱，如果缺钱早就搞直播了，不会搞田径。＂这种率真，这份坦诚，在当下实属难得。02出生于单亲家庭的她，与母亲熊艳的关系亲密无间。在成都大运会上摘得银牌的那一刻，她泪流满面地对妈妈说：＂妈妈，我达奥运标了！＂那一刻，看台上的母亲也热泪盈眶，对女儿喊道：＂你是我的骄傲，是我们全国人民的骄傲！妮子，你最棒！＂母女俩同时喊出＂巴黎见＂的约定。关于手臂纹身的争议，她选择了尊重规则，用胶布遮挡，但从不否认这是自己的一部分。她的生活态度是：做真实的自己，不需要取悦所有人。当网友拿她与其他运动员相比较时，她没有参与这种无谓的争论。在她看来，田径场上唯有成绩才是硬道理，比美不是她的目标。03＂面包和爱情，其实我已经有面包了＂，这句话折射出她对生活的清醒认知。经济独立带来的不只是物质自由，更是择偶观的自主权。社交平台上，当有人猜测她与男子100米新星乔臻的关系时，她的母亲出面澄清：＂她没有恋爱，目前主要精力都在训练上。＂运动生涯与个人生活，她似乎总能找到平衡点。从富顺县的小姑娘到闪耀奥运赛场的国家队选手，她的每一步都走得踏实而有力。当被问及对未来的期许，她说希望能在亚运会和奥运会上取得更好的成绩。她的目光始终盯着前方更高的栏架，不被当下的成就所满足。那个在赛道上奔跑的身影，那个谈论理想型的率真女孩，正用自己的方式告诉世界：现代女性可以独立自主，可以追求梦想，也可以拥有幸福的爱情。跨栏不只是她的专业项目，更是她人生的隐喻。看她如何在各种人生栏架前，调整步频，起跨冲刺，勇往直前！点击即可关注我👇👇愿欢乐常驻您身边",
        "author": "呆头鱼闲聊1",
        "time": "2025-04-08 23:33"
    }
]