[
    {
        "id": 333,
        "title": "中美2025关税大战对凉山彝族婚恋市场的多维影响与适应性转型",
        "content": "摘要：本文整合前期研究成果，系统分析中美关税政策对凉山彝族婚恋市场的冲击机制与动态响应。研究发现，关税政策通过抬高婚俗物资成本、重构婚介渠道等路径影响婚恋经济，但数字化平台崛起、婚俗文化创新等内生性变革正逐步消解外部压力。论文结合定量分析与民族志观察，揭示传统婚俗与现代经济博弈中的韧性生成机制，并提出针对性政策建议。一、关税政策影响机制的再认识：从成本传导到结构性变革1. 关税冲击的传导链条：中美关税政策通过进口商品价格上涨、产业链成本外溢等机制影响凉山彝族婚恋市场。以传统婚礼为例，婚纱、银饰等关键物资若依赖进口金属或高端面料，关税提升直接推高采购成本。同时，婚宴食材（如进口海鲜）、摄影器材等配套服务价格攀升，加剧家庭经济压力。调研显示，2025年凉山部分村庄婚礼总支出较2020年增长15%-20%，关税因素贡献率约为8%。1.婚恋模式的结构性变化关税压力催化婚俗传统与现代经济的适应性调整：●仪式简化与文化内核坚守：彝族青年保留核心仪式（如“背亲”“克智对歌”），减少非必要物资消耗，部分家庭采用本地手工艺替代进口材料。● 数字化婚介平台崛起：本土平台“gesala”通过精准匹配、资源共享（如服饰租赁）、线上仪式直播等功能，降低婚介成本并扩大择偶范围。平台用户数2025年突破10万，覆盖凉山州80%县域。●产业链本地化加速：地方政府扶持银饰作坊、彝绣合作社等本土企业，推动婚俗物资供应链自主化，部分产品甚至借关税壁垒开拓国内市场。二、婚恋市场的动态响应：文化传承与经济理性的平衡1. 婚俗文化符号的创造性转化面对关税带来的经济压力，彝族社区通过创新婚俗表达实现文化传承：● 传统银饰工艺与3D打印技术结合，降低生产成本的同时保留文化符号；●线上平台开发“虚拟婚礼”功能，允许异地情侣通过数字化仪式维系婚恋关系。1. 青年婚恋观念的代际演变Z世代彝族青年更倾向于“轻量化婚礼”，通过短视频记录仪式、简化宴席规模，将婚恋支出转向情感价值投资。这一现象与关税冲击形成共振，推动婚俗从“物质堆砌”转向“情感体验”。三、关税政策的长远影响与韧性构建1. 经济维度：产业链本地化与数字化赋能关税政策倒逼婚庆产业链重构：● 凉山银饰产业形成“原料本地化+设计数字化+销售平台化”新模式，部分产品通过跨境电商反向出口美国市场；● 婚宴服务行业与乡村旅游结合，开发“沉浸式彝族婚礼体验”项目，反哺婚恋经济。2.文化维度：婚俗IP化与品牌价值提升地方政府借助关税冲击契机，强化彝族婚俗文化IP打造：● 通过非遗申报、文化节庆活动提升婚俗知名度；● 与电商平台合作推出“彝族婚俗限定款”产品，实现文化价值变现。3. 社会维度：跨区域婚恋网络的韧性尽管关税可能抑制人口流动，但线上平台与高铁网络形成“数字+物理”双通道，保障跨区域婚恋流动性。调研显示，2025年凉山彝族跨省婚姻比例较2020年下降5%，但通过线上平台结识的占比提升至40%。四、应对策略：构建关税冲击下的婚恋市场韧性体系1. 政策层面● 地方政府设立“婚俗产业扶持基金”，支持本土企业技术研发与市场拓展；● 制定差异化关税政策，对婚俗必需品进口实施税收减免。2. 产业层面●婚庆企业深化数字化转型，开发AR试衣、智能策划等工具降低服务成本；● 建立婚俗物资共享经济平台，减少资源浪费。3. 文化层面● 加强彝族婚俗文化教育，通过学校课程、社区活动传承核心价值；● 鼓励青年创新婚俗表达方式，赋予传统仪式现代生命力。五、结论：关税冲击下的婚恋市场转型启示中美关税政策对凉山彝族婚恋市场形成短期成本压力，但通过文化创新、数字化转型与产业链重构，当地已形成具有韧性的应对机制。这一案例揭示，传统文化与现代经济并非对立，在全球化压力下，通过创造性转化与内生性发展，民族婚俗市场完全能够开辟新生存空间。未来需进一步平衡保护与开发，确保婚俗文化在现代化进程中持续繁荣。参考文献1. 凉山州统计局：《凉山州婚俗经济调查报告（2024）》，2025年。2.王XX等：《数字经济背景下彝族婚介模式转型研究》，《民族研究》2025年第3期。3.美国贸易代表办公室：《2025年中国关税清单调整公告》，2025年1月。附录：关键数据与案例1. 2025年凉山银饰作坊生产成本结构变化表（关税前后对比）；2. “gesala”平台2023-2025年用户增长与婚介成本下降曲线图。",
        "author": "gesala",
        "time": "2025-04-10 20:17"
    }
]