[
    {
        "id": 722,
        "title": "婚恋教育设为大学必修？很有必要！",
        "content": "婚恋教育设为大学必修？很有必要！近日，随着两会的召开，各位委员、代表都提出了很多热点议题。全国政协于欣伟委员发言：”当前大学生婚恋情感教育缺失，对感情和性的认识大多停留在生理卫生知识层面，在面对感情和恋爱挫折时，容易出现偏激失控，甚至做出极端行为。”她建议：将婚恋教育设为高校必修课，结合案例编教材。这一提案在网上展开了激烈的讨论。婚恋，包括婚姻和恋爱，我们先从恋爱说起。从我们上学开始，关于恋爱的一个基本印象就是：那是不对的。至少在大学之前，谈恋爱都被视为“早恋”，家长、教师，甚至整个社会都在尽力使学生远离有关恋爱的一切。依据我们各方面的教育情况，这样的做法还是有利于我们在中学的学习生活的。但是，到了大学后，没有了家长对于恋爱的反对以及校规对于恋爱的束缚，“自由”的大学生们好像脱缰的野马，肆意驰骋在“爱情”的草原上。对异性有好感本身是一件非常正常的事情，但是，恋爱关系作为人际关系的一种，它本身是非常复杂的，可由于我们在此之前并没有接受到与之相关的正向教育，在处理恋爱问题时，很有可能出现比较偏激的做法，不能很好地处理这些问题除此之外，由于没有正式的教育，学生会很容易从其他途径获取相关知识，比如，言情小说、恋爱偶像剧等等。但是我们可以看到，那些作品里描绘的恋爱大多是与现实脱节的，照搬到现实生活中就有可能产生问题。在生活里，有因为恋爱双方发生矛盾，而伤害他人或者自残自杀的；有因为恋爱受挫而萎靡不振，酗酒自残的；有因为不能控制自己感情，荒废学业的……这些悲剧有很多原因：不懂得如何让自己的爱温暖对方，不懂得在爱里保持和保护自我，不懂得在该告别时潇洒转身……所以是该有这么一门课来教会我们，如何处理恋爱问题了。再来说婚姻，大学生，二十上下的年纪，其实很难想象婚姻的样子。但是，刚刚成年的大学生，大部分对于婚姻还是十分向往的。我们总想着婚姻是十分美好的，所以可能会轻易做出影响一生的决定。可是，我们真的了解婚姻吗？我们知道那意味着什么吗？至少，婚姻是两个人将要在余生共同承担困难、共同支撑一个家，对方很有可能是陪你最久的人。婚姻意味着责任，意味着双方在没有任何血缘关系的情况下，要在漫长时间的洗礼和平淡的生活中，包容对方，一日三餐，柴米油盐。这些只是冰山一角，除此之外，婚姻还有伦理道德、法律法规等方面的意义。很多人都读过钱钟书先生的一句话：“婚姻是一座围城,城外的人想进去,城里的人想出来。”可见，婚姻是极其复杂的。就像于欣伟委员说的那样：“大学生是社会的重要人才储备群体，他们的婚恋观不仅折射出个体人生价值取向，某种程度上也代表着未来社会婚姻家庭的发展趋势。加强大学生婚恋教育，有利于社会和谐发展，为人口素质提高奠基。”还有一个重点是“结合案例编教材”，这是“教”的问题。若真的开了课，开始的起步阶段肯定会出现很多不足，这当然不是件容易的事。希望相关部门能够认真研究，制定出好的方案和措施，在大学阶段能够给大学生一些婚恋观上的帮助。扫码关注我们文案 | 潘子涵音频 | 张敬涵后期 | 任亦萱排版 | 李杰出品 | 西电FM广播站-E N D-",
        "author": "西电广播站",
        "time": "2021-03-17 21:00"
    }
]