[
    {
        "id": 1117,
        "title": "新修订《婚姻登记条例》自5月10日起施行！",
        "content": "4月9日，新修订的《婚姻登记条例》公布，自2025年5月10日起施行。条例全文共6章28条，包括“总则”“结婚登记”“离婚登记”“婚姻登记档案管理”“法律责任”“附则”等内容。条例修订的主要内容包含三个方面：一是增加婚姻家庭服务工作内容，规定县级以上地方人民政府加强综合性婚姻家庭服务指导工作和婚姻家庭辅导服务体系建设，倡导文明婚俗，促进家庭和谐，引导树立正确的婚恋观、生育观、家庭观；二是实行婚姻登记“全国通办”，深化婚姻登记制度改革，进一步提高婚姻登记的便利性；三是优化婚姻登记服务，规定县级以上地方人民政府采取措施提升婚姻登记服务水平，加强婚姻登记场所规范化、便利化建设。推 荐 阅 读▶【央媒看青海】中国故事｜雪豹“凌小蛰”康复日记▶明后天，西宁将有吹风、沙尘、降温天气▶西宁市教育局最新公告▶青海乌兰泉沟墓出土王冠重现华光▶@考生们，2025年注册会计师考试已开启报名来源：央视新闻以上图文，贵在分享，版权归原作者及原出处所有，内容仅为作者观点，并不代表本公众号立场。如涉及版权等问题，请及时与我们联系。转载请注明出处责编：侯桂青    编辑：于亦祥",
        "author": "视讯青海",
        "time": "2025-04-10 09:28"
    }
]