{
    "id": 1452,
    "summary": "资深红娘万阿姨认为24、25岁是女性结婚的最佳年龄，并建议年轻人早婚早育，因为女性年龄大了养孩子质量不行，而男性可以“拉差价”。她强调了年轻人择偶要求不宜过高，否则会成为“剩男”。然而，数据显示上海女性初婚初育年龄大幅提高，与全国相比，上海男女初婚年龄提高速度高于全国水平，女性初婚年龄提高幅度高于男性。网友对此表示女性更不着急结婚。晚婚现象的原因多元，包括年轻人追求独立和教育，以及社会压力等。",
    "keywords": [
        "结婚年龄",
        "女性",
        "红娘",
        "剩男",
        "择偶"
    ],
    "keyword_relations": {
        "结婚年龄,女性": "女性结婚的最佳年龄被认为在24、25岁",
        "结婚年龄,红娘": "红娘建议年轻人早婚早育",
        "女性,剩男": "女性择偶要求高可能导致成为剩男",
        "红娘,择偶": "红娘强调择偶要求不宜过高",
        "剩男,择偶": "择偶要求高是成为剩男的原因之一"
    },
    "sentiment": "中性"
}