{
    "id": 1444,
    "summary": "文章通过最高人民法院公布的离婚纠纷司法大数据，揭示了现代婚姻中的三个残酷真相：女性提出离婚的比例高，婚姻质量被重视，以及婚姻中的不和问题。文章指出，女性经济独立和对婚姻质量的要求提高是离婚率上升的主要原因。同时，文章强调了感情不和是导致离婚的主要因素，包括三观不合、性格不合等。文章还提到，婚后2-7年是婚姻破裂的高发期，尤其是3-4年，许多婚姻因为婚前了解不足和婚后问题凸显而破裂。最后，文章呼吁重视婚姻的经营，珍惜彼此的付出和陪伴。",
    "keywords": [
        "离婚纠纷",
        "女性提出离婚",
        "婚姻质量",
        "感情不和",
        "婚姻破裂"
    ],
    "keyword_relations": {
        "离婚纠纷,女性提出离婚": "离婚纠纷中女性提出离婚的比例高，反映了女性在婚姻中的主动权和经济独立性",
        "女性提出离婚,婚姻质量": "女性提出离婚与对婚姻质量的重视有关，女性不再忍受低质量婚姻",
        "婚姻质量,感情不和": "婚姻质量的下降往往是感情不和的结果，感情不和是离婚的主要原因",
        "感情不和,婚姻破裂": "感情不和直接导致婚姻破裂，特别是在婚后2-7年的高发期",
        "婚姻破裂,离婚纠纷": "婚姻破裂最终表现为离婚纠纷，法院审理的案件数量反映了这一现象"
    },
    "sentiment": "负面"
}