{
    "id": 407,
    "summary": "本文讲述了一种名为“杀猪盘”的新型诈骗方式，该诈骗通过在社交媒体上建立信任后诱导受害者投资，最终骗取钱财。文章通过一个三亚小伙小胡的案例，揭示了诈骗分子如何通过建立感情关系、怂恿投资、诱导大量投入、阻止提现和最终消失的五个步骤进行诈骗。文章最后提醒公众在网络交友和金钱往来时提高警惕，避免落入诈骗陷阱。",
    "keywords": [
        "杀猪盘",
        "诈骗",
        "社交媒体",
        "投资",
        "信任"
    ],
    "keyword_relations": {
        "杀猪盘,诈骗": "杀猪盘是一种诈骗方式",
        "诈骗,社交媒体": "诈骗通过社交媒体实施",
        "社交媒体,信任": "在社交媒体上建立信任是诈骗的第一步",
        "信任,投资": "建立信任后诱导受害者进行投资",
        "投资,钱财": "投资最终导致受害者钱财被骗"
    },
    "sentiment": "警示"
}