{
    "id": 484,
    "summary": "文章探讨了性别差异，特别是智力和性格上的性别差异。研究表明，男性和女性在智力上没有显著差异，但在特定领域各有所长。社会认知和性别刻板印象对两性差异有重大影响，而性格上的差异更多是后天社会构建的结果。文章强调，个人的决策权在自己手中，不受性别刻板印象的限制。",
    "keywords": [
        "性别差异",
        "智力",
        "性格",
        "社会认知",
        "刻板印象"
    ],
    "keyword_relations": {
        "性别差异,智力": "性别差异在智力上的研究显示男女没有显著差异",
        "性别差异,性格": "性格上的差异被认为是社会构建的结果，非先天性别差异",
        "智力,社会认知": "智力研究显示男性和女性在社会认知和语言理解方面各有所长",
        "性格,刻板印象": "性格差异受社会刻板印象的影响，而非生理性别决定"
    },
    "sentiment": "中性"
}