{
    "id": 439,
    "summary": "文章探讨了婚姻的美好和现实挑战，通过名人婚姻故事展示了婚姻中的相互支持和理解。同时，介绍了国务院通过的《婚姻登记条例（修订草案）》带来的婚姻登记便利，以及政府为减轻年轻人结婚负担所采取的措施。文章鼓励年轻人树立正确的婚恋观，勇敢追求幸福。",
    "keywords": [
        "婚姻",
        "名人婚恋启示",
        "婚姻登记新变革",
        "幸福",
        "政策"
    ],
    "keyword_relations": {
        "婚姻,名人婚恋启示": "名人婚恋启示是婚姻中相互支持和理解的典范",
        "婚姻,婚姻登记新变革": "婚姻登记新变革为婚姻提供了便利，增强了人们对婚姻的期待",
        "婚姻,幸福": "婚姻是追求幸福的一种方式，需要双方共同努力",
        "婚姻,政策": "政策的出台旨在减轻年轻人结婚负担，促进婚姻和生育",
        "名人婚恋启示,婚姻登记新变革": "名人婚恋启示通过个人故事展示了婚姻的美好，而婚姻登记新变革则为实现这种美好提供了制度支持"
    },
    "sentiment": "正面"
}