{
    "id": 417,
    "summary": "唐艺昕和张若昀这对模范夫妻公开支持离婚自由，认为婚姻不应是束缚而是自由选择。他们的观点打破了传统婚姻观念，强调平等与自由，认为离婚是重新开始的选择。这一观点在网友中引起争议，一部分人认为他们的观点前卫，代表新时代婚姻的开放性和理性，而另一部分人则持怀疑态度。两人的穿搭和神态也体现了他们对婚姻的态度，唐艺昕简单优雅的穿着和淡定的微笑，张若昀深邃的眼神和冷静气质，都暗示着婚姻是双方选择的结果。",
    "keywords": [
        "唐艺昕",
        "张若昀",
        "离婚自由",
        "婚姻观念",
        "新时代"
    ],
    "keyword_relations": {
        "唐艺昕,张若昀": "唐艺昕和张若昀是一对模范夫妻，公开支持离婚自由",
        "离婚自由,婚姻观念": "离婚自由是唐艺昕和张若昀提出的新婚姻观念的一部分",
        "婚姻观念,新时代": "他们的婚姻观念代表了新时代对婚姻的开放性和理性看法",
        "唐艺昕,新时代": "唐艺昕的穿搭和神态体现了新时代女性对婚姻的态度",
        "张若昀,新时代": "张若昀的深邃眼神和冷静气质暗示了新时代男性对婚姻的看法"
    },
    "sentiment": "中性"
}