{
    "id": 535,
    "summary": "文章讨论了市场上一些不必要的性别化商品，指出这些商品的性别化特征是毫无意义的。例如，薯片袋、地球仪、电池、字母表和海绵等商品被赋予性别特征，而实际上这些特征对于商品的使用和功能并无实际影响。文章通过列举这些商品的例子，批评了这种性别化趋势，并呼吁读者分享他们遇到的类似产品。",
    "keywords": [
        "性别化商品",
        "薯片袋",
        "地球仪",
        "电池",
        "海绵"
    ],
    "keyword_relations": {
        "性别化商品,薯片袋": "性别化商品包括了薯片袋，后者被赋予了男性特征",
        "性别化商品,地球仪": "性别化商品的例子之一是地球仪，也被性别化",
        "性别化商品,电池": "电池是性别化商品中的一个例子，被赋予性别特征",
        "性别化商品,海绵": "海绵作为性别化商品，被认为具有母性特征",
        "薯片袋,地球仪": "薯片袋和地球仪都是被性别化的商品，无实际必要",
        "电池,海绵": "电池和海绵作为性别化商品，同样无实际必要"
    },
    "sentiment": "负面"
}