{
    "id": 707,
    "summary": "全国政协委员于欣伟提出应将婚恋教育设为大学必修课，以应对大学生婚恋情感教育的缺失和由此引发的心理健康问题。她指出，大学生的婚恋观不仅影响个人，也反映未来社会的发展趋势。当前，言情小说、电视剧等媒体传播的不切实际的婚恋观念对大学生产生不良影响。于欣伟建议构建三维婚恋教育模式，包括学校、家庭和社会教育，并推动师资专业化。此建议引发网友热议，意见不一。",
    "keywords": [
        "婚恋教育",
        "大学生",
        "心理健康",
        "媒体影响",
        "教育体系"
    ],
    "keyword_relations": {
        "婚恋教育,大学生": "婚恋教育对大学生的心理健康和婚恋观有重要影响",
        "大学生,心理健康": "大学生的心理健康受婚恋情感教育的影响",
        "媒体影响,教育体系": "媒体对大学生的婚恋观念有影响，需要通过教育体系来纠正",
        "婚恋教育,教育体系": "婚恋教育需要构建和完善教育体系来实施",
        "心理健康,媒体影响": "媒体影响可能导致大学生心理健康问题"
    },
    "sentiment": "中性"
}