{
    "id": 1118,
    "summary": "江苏常州和浙江杭州两地民政部门公布了2022年度的婚姻大数据。杭州结婚登记数增加，离婚登记数微增，复婚登记数保持稳定。常州结婚人数有所下降，离婚人数增加。两地男女结婚登记平均年龄均在30岁以上，杭州男性平均初婚年龄28.8岁，女性27.5岁，常州市结婚登记平均年龄为31.05岁。杭州“姐弟恋”比例持续上升，常州市24岁以下年龄段男女结婚人数相差悬殊。团中央提案创造有利条件鼓励青年生育，新修订的妇女权益保障法施行，强调消除就业性别歧视，保护妇女权益。",
    "keywords": [
        "婚姻大数据",
        "结婚登记",
        "离婚登记",
        "平均年龄",
        "姐弟恋",
        "妇女权益",
        "生育政策"
    ],
    "keyword_relations": {
        "婚姻大数据,结婚登记": "结婚登记是婚姻大数据的一部分，反映了两地的结婚情况",
        "结婚登记,离婚登记": "结婚登记和离婚登记是婚姻状况的两个方面，反映了婚姻的稳定性",
        "平均年龄,结婚登记": "结婚登记的平均年龄是衡量社会婚姻状况的一个重要指标",
        "姐弟恋,结婚登记": "姐弟恋比例的变化反映了结婚登记中的性别年龄差异",
        "妇女权益,生育政策": "妇女权益保障法的施行与生育政策相关，旨在保护妇女权益，促进生育",
        "生育政策,结婚登记": "生育政策可能影响结婚登记数，政策的制定和实施对婚姻状况有间接影响"
    },
    "sentiment": "中性"
}