{
    "id": 1283,
    "summary": "外语外贸学院心理辅导站Sunny Mood工作室联合向阳育心辅导员工作室举办了一场心理健康讲座，主题为“PDP动物行为风格与在婚恋中呵护身心健康”。讲座由洪小加老师主讲，旨在帮助大学生了解自己的PDP动物行为风格，树立正确的婚恋观。通过小游戏和PDP风格测试，洪老师引导学生了解不同动物行为风格的特点，并探讨了亲密关系中的婚恋问题。讲座强调了在婚恋中如何通过有效方式呵护身心健康，提升沟通效率，最终达到双方身心健康的目标。",
    "keywords": [
        "心理健康讲座",
        "PDP动物行为风格",
        "婚恋",
        "身心健康",
        "沟通效率"
    ],
    "keyword_relations": {
        "心理健康讲座,PDP动物行为风格": "心理健康讲座通过PDP动物行为风格帮助学生了解自己",
        "PDP动物行为风格,婚恋": "PDP动物行为风格在婚恋中的作用和影响",
        "婚恋,身心健康": "婚恋中的身心健康是讲座的核心议题",
        "身心健康,沟通效率": "身心健康与沟通效率的提升是讲座的目标"
    },
    "sentiment": "正面"
}